mx82/__init__.py
mx82/funcs.py
mx82-0.2.4.dist-info/LICENSE
mx82-0.2.4.dist-info/METADATA
mx82-0.2.4.dist-info/WHEEL
mx82-0.2.4.dist-info/RECORD
